swel/__init__.py
swel/buoy.py
swel/swel.py
swel/tests/__init__.py
swel/tests/buoy_test.py
swel-0.0.1.dist-info/METADATA
swel-0.0.1.dist-info/RECORD
swel-0.0.1.dist-info/WHEEL
swel-0.0.1.dist-info/namespace_packages.txt
swel-0.0.1.dist-info/top_level.txt
